mcp_llm_bridge/__init__.py
mcp_llm_bridge/bridge.py
mcp_llm_bridge/config.py
mcp_llm_bridge/create_test_db.py
mcp_llm_bridge/llm_client.py
mcp_llm_bridge/main.py
mcp_llm_bridge/mcp_client.py
mcp_llm_bridge/tools.py
mseep_mcp_llm_bridge-0.1.4.dist-info/licenses/LICENSE.md
mseep_mcp_llm_bridge-0.1.4.dist-info/METADATA
mseep_mcp_llm_bridge-0.1.4.dist-info/WHEEL
mseep_mcp_llm_bridge-0.1.4.dist-info/top_level.txt
mseep_mcp_llm_bridge-0.1.4.dist-info/RECORD
